Metadata-Version: 2.1
Name: code128bgen
Version: 0.1.0
Summary: Generation of the Code128b barcode
Home-page: https://github.com/damiandennis/code128bgen
Author: Damian Dennis
Author-email: damiandennis@gmail.com
License: UNKNOWN
Platform: UNKNOWN
Requires-Python: >=3.6
